pyquizAPI/__init__.py
pyquizAPI/client/__init__.py
pyquizAPI/client/utils.py
pyquizAPI-0.0.14.dist-info/LICENSE
pyquizAPI-0.0.14.dist-info/METADATA
pyquizAPI-0.0.14.dist-info/WHEEL
pyquizAPI-0.0.14.dist-info/top_level.txt
pyquizAPI-0.0.14.dist-info/RECORD
