Metadata-Version: 2.1
Name: pyquizAPI
Version: 0.0.14
Summary: API Client Wrapper for QuizAPI.io
Home-page: https://github.com/msherburne/pyquizAPI
Author: Mathieu Sherburne
License: MIT
Platform: UNKNOWN
Classifier: Programming Language :: Python :: 3
Classifier: License :: OSI Approved :: MIT License
Classifier: Operating System :: OS Independent
Requires-Python: >=3.8
License-File: LICENSE
Requires-Dist: requests
